HISTORY.rst
LICENCE.txt
MANIFEST.in
README.rst
setup.py
datebook/__init__.py
datebook/admin.py
datebook/assets.py
datebook/calendars.py
datebook/crumbs.py
datebook/markup.py
datebook/mixins.py
datebook/models.py
datebook/settings.py
datebook/urls.py
datebook/forms/__init__.py
datebook/forms/crispies.py
datebook/forms/day.py
datebook/forms/daymodel.py
datebook/forms/month.py
datebook/forms/year.py
datebook/locale/es/LC_MESSAGES/django.mo
datebook/locale/es/LC_MESSAGES/django.po
datebook/locale/fr/LC_MESSAGES/django.mo
datebook/locale/fr/LC_MESSAGES/django.po
datebook/migrations/0001_initial.py
datebook/migrations/__init__.py
datebook/south_migrations/0001_initial.py
datebook/south_migrations/0002_auto__add_field_dayentry_overtime.py
datebook/south_migrations/0003_auto__add_daymodel__add_unique_daymodel_author_title.py
datebook/south_migrations/0004_auto__add_field_datebook_notes.py
datebook/south_migrations/__init__.py
datebook/static/css/datebook_app.css
datebook/static/fonts/datebook.eot
datebook/static/fonts/datebook.svg
datebook/static/fonts/datebook.ttf
datebook/static/fonts/datebook.woff
datebook/static/js/datebook/calendar.js
datebook/static/js/datebook/day_form.js
datebook/static/js/jquery/jquery.timepicker.js
datebook/static/js/jquery/moment.js
datebook/static/js/jquery/pikaday.js
datebook/templates/datebook/author_index.html
datebook/templates/datebook/base.html
datebook/templates/datebook/include_css.html
datebook/templates/datebook/include_js.html
datebook/templates/datebook/index.html
datebook/templates/datebook/week.html
datebook/templates/datebook/year.html
datebook/templates/datebook/day/delete.html
datebook/templates/datebook/day/detail_fragment.html
datebook/templates/datebook/day/form.html
datebook/templates/datebook/day/form_fragment.html
datebook/templates/datebook/daymodel/index.html
datebook/templates/datebook/markup/_text_field_djangocodemirror_js.html
datebook/templates/datebook/markup/_text_markup_render.html
django_datebook.egg-info/PKG-INFO
django_datebook.egg-info/SOURCES.txt
django_datebook.egg-info/dependency_links.txt
django_datebook.egg-info/not-zip-safe
django_datebook.egg-info/requires.txt
django_datebook.egg-info/top_level.txt